Metadata-Version: 1.0
Name: danil2
Version: 0.0
Summary: P7-20R urok oop 10.12.22
Home-page: UNKNOWN
Author: UNKNOWN
Author-email: auelbeknurzhan69@gmail.com
License: UNKNOWN
Platform: UNKNOWN
